{
  "query": "22271.sql",
  "engine": "duckdb",
  "query_latency_ms": 1742.621925,
  "root": {
    "id": 1,
    "op": "Sort",
    "name": "ORDER_BY",
    "children": [
      {
        "id": 5,
        "op": "Aggregate",
        "name": "HASH_GROUP_BY",
        "children": [
          {
            "id": 9,
            "op": "Join",
            "name": "HASH_JOIN",
            "children": [
              {
                "id": 13,
                "op": "Filter",
                "name": "FILTER",
                "children": [
                  {
                    "id": 14,
                    "op": "Join",
                    "name": "LEFT_DELIM_JOIN",
                    "children": [
                      {
                        "id": 15,
                        "op": "Join",
                        "name": "HASH_JOIN",
                        "children": [
                          {
                            "id": 16,
                            "op": "Aggregate",
                            "name": "HASH_GROUP_BY",
                            "children": [
                              {
                                "id": 18,
                                "op": "Scan",
                                "name": "READ_PARQUET",
                                "children": [],
                                "metrics": {
                                  "elapsed_ms": 186.5743349999999,
                                  "rows_in": null,
                                  "rows_out": 11795244,
                                  "row_size_in_bytes": 0.0,
                                  "row_size_out_bytes": 10.125
                                },
                                "columns": {
                                  "active": [
                                    "posthistory.id",
                                    "posthistory.posthistorytypeid",
                                    "posthistory.userid"
                                  ]
                                },
                                "details": {
                                  "scan": {
                                    "table": "posthistory",
                                    "columns": [
                                      "id",
                                      "posthistorytypeid",
                                      "userid"
                                    ],
                                    "pushdown_predicates": [],
                                    "delim_index": null,
                                    "fixed_widths": [
                                      4,
                                      2,
                                      4
                                    ],
                                    "varwidth": [
                                      false,
                                      false,
                                      false
                                    ]
                                  }
                                }
                              }
                            ],
                            "metrics": {
                              "elapsed_ms": 280.12034400000016,
                              "rows_in": 11795244,
                              "rows_out": 374117,
                              "row_size_in_bytes": 8.125,
                              "row_size_out_bytes": 28.0
                            },
                            "columns": {
                              "active": [
                                "posthistory.userid",
                                "posthistory.posthistorytypeid"
                              ]
                            },
                            "details": {
                              "aggregate": {
                                "group_keys": [
                                  "#0"
                                ],
                                "aggregates": [
                                  "count_star()",
                                  "sum(#1)",
                                  "sum(#2)"
                                ],
                                "algorithm": null
                              }
                            }
                          },
                          {
                            "id": 19,
                            "op": "Join",
                            "name": "HASH_JOIN",
                            "children": [
                              {
                                "id": 20,
                                "op": "Scan",
                                "name": "READ_PARQUET",
                                "children": [],
                                "metrics": {
                                  "elapsed_ms": 87.61910099999999,
                                  "rows_in": null,
                                  "rows_out": 1260710,
                                  "row_size_in_bytes": 0.0,
                                  "row_size_out_bytes": 34.893136407262574
                                },
                                "columns": {
                                  "active": [
                                    "users.id",
                                    "users.reputation",
                                    "users.displayname"
                                  ]
                                },
                                "details": {
                                  "scan": {
                                    "table": "users",
                                    "columns": [
                                      "id",
                                      "reputation",
                                      "displayname"
                                    ],
                                    "pushdown_predicates": [],
                                    "delim_index": null,
                                    "fixed_widths": [
                                      4,
                                      4,
                                      12
                                    ],
                                    "varwidth": [
                                      false,
                                      false,
                                      true
                                    ]
                                  }
                                }
                              },
                              {
                                "id": 21,
                                "op": "Aggregate",
                                "name": "HASH_GROUP_BY",
                                "children": [
                                  {
                                    "id": 25,
                                    "op": "Window",
                                    "name": "WINDOW",
                                    "children": [
                                      {
                                        "id": 26,
                                        "op": "Scan",
                                        "name": "READ_PARQUET",
                                        "children": [],
                                        "metrics": {
                                          "elapsed_ms": 26.110290000000003,
                                          "rows_in": null,
                                          "rows_out": 9927,
                                          "row_size_in_bytes": 0.0,
                                          "row_size_out_bytes": 22.25
                                        },
                                        "columns": {
                                          "active": [
                                            "posts.id",
                                            "posts.posttypeid",
                                            "posts.creationdate",
                                            "posts.viewcount",
                                            "posts.owneruserid"
                                          ]
                                        },
                                        "details": {
                                          "scan": {
                                            "table": "posts",
                                            "columns": [
                                              "id",
                                              "posttypeid",
                                              "creationdate",
                                              "viewcount",
                                              "owneruserid"
                                            ],
                                            "pushdown_predicates": [
                                              "creationdate>='2024-09-01 12:34:56'::TIMESTAMP"
                                            ],
                                            "delim_index": null,
                                            "fixed_widths": [
                                              4,
                                              2,
                                              8,
                                              4,
                                              4
                                            ],
                                            "varwidth": [
                                              false,
                                              false,
                                              false,
                                              false,
                                              false
                                            ]
                                          }
                                        }
                                      }
                                    ],
                                    "metrics": {
                                      "elapsed_ms": 6.405396,
                                      "rows_in": 9927,
                                      "rows_out": 9927,
                                      "row_size_in_bytes": 22.25,
                                      "row_size_out_bytes": 30.25
                                    },
                                    "columns": {
                                      "active": [
                                        "posts.owneruserid",
                                        "posts.creationdate"
                                      ]
                                    },
                                    "details": {
                                      "window": {
                                        "expressions": [
                                          "ROW_NUMBER() OVER (PARTITION BY owneruserid ORDER BY creationdate DESC NULLS LAST)"
                                        ]
                                      }
                                    }
                                  }
                                ],
                                "metrics": {
                                  "elapsed_ms": 0.570484,
                                  "rows_in": 9927,
                                  "rows_out": 4530,
                                  "row_size_in_bytes": 12.25,
                                  "row_size_out_bytes": 36.0
                                },
                                "columns": {
                                  "active": [
                                    "posts.owneruserid",
                                    "posts.posttypeid",
                                    "posts.viewcount"
                                  ]
                                },
                                "details": {
                                  "aggregate": {
                                    "group_keys": [
                                      "#0"
                                    ],
                                    "aggregates": [
                                      "count_star()",
                                      "sum(#1)",
                                      "sum(#2)",
                                      "avg(#3)"
                                    ],
                                    "algorithm": null
                                  }
                                }
                              }
                            ],
                            "metrics": {
                              "elapsed_ms": 20.547939000000003,
                              "rows_in": 1265240,
                              "rows_out": 1260710,
                              "rows_in_left": 1260710,
                              "rows_in_right": 4530,
                              "row_size_in_left_bytes": 34.893136407262574,
                              "row_size_in_right_bytes": 36.0,
                              "row_size_out_bytes": 70.89313640726257
                            },
                            "columns": {
                              "active": [
                                "users.id",
                                "posts.owneruserid"
                              ]
                            },
                            "details": {
                              "join": {
                                "join_type": "LEFT",
                                "condition": "id = owneruserid",
                                "left_keys": [],
                                "right_keys": [],
                                "delim_index": null
                              }
                            }
                          }
                        ],
                        "metrics": {
                          "elapsed_ms": 155.04413800000003,
                          "rows_in": 1634827,
                          "rows_out": 1260710,
                          "rows_in_left": 374117,
                          "rows_in_right": 1260710,
                          "row_size_in_left_bytes": 28.0,
                          "row_size_in_right_bytes": 70.89313640726257,
                          "row_size_out_bytes": 98.89313640726257
                        },
                        "columns": {
                          "active": [
                            "posthistory.userid",
                            "users.id"
                          ]
                        },
                        "details": {
                          "join": {
                            "join_type": "RIGHT",
                            "condition": "userid = id",
                            "left_keys": [],
                            "right_keys": [],
                            "delim_index": null
                          }
                        }
                      },
                      {
                        "id": 27,
                        "op": "Join",
                        "name": "HASH_JOIN",
                        "children": [
                          {
                            "id": 28,
                            "op": "Scan",
                            "name": "COLUMN_DATA_SCAN",
                            "children": [],
                            "metrics": {
                              "elapsed_ms": 5.270301000000007,
                              "rows_in": null,
                              "rows_out": 1260710,
                              "row_size_in_bytes": 0.0,
                              "row_size_out_bytes": 0.0
                            },
                            "columns": {
                              "active": []
                            },
                            "details": {
                              "scan": {
                                "table": "",
                                "columns": [],
                                "pushdown_predicates": [],
                                "delim_index": null,
                                "fixed_widths": [],
                                "varwidth": []
                              }
                            }
                          },
                          {
                            "id": 30,
                            "op": "Join",
                            "name": "HASH_JOIN",
                            "children": [
                              {
                                "id": 31,
                                "op": "Scan",
                                "name": "DELIM_SCAN",
                                "children": [],
                                "metrics": {
                                  "elapsed_ms": 0.0,
                                  "rows_in": null,
                                  "rows_out": 1260710,
                                  "row_size_in_bytes": 0.0,
                                  "row_size_out_bytes": 8.0
                                },
                                "columns": {
                                  "active": []
                                },
                                "details": {
                                  "scan": {
                                    "table": "",
                                    "columns": [],
                                    "pushdown_predicates": [],
                                    "delim_index": "1",
                                    "fixed_widths": [],
                                    "varwidth": []
                                  }
                                }
                              },
                              {
                                "id": 33,
                                "op": "Filter",
                                "name": "FILTER",
                                "children": [
                                  {
                                    "id": 34,
                                    "op": "Scan",
                                    "name": "READ_PARQUET",
                                    "children": [],
                                    "metrics": {
                                      "elapsed_ms": 13.74807599999999,
                                      "rows_in": null,
                                      "rows_out": 1273148,
                                      "row_size_in_bytes": 0.0,
                                      "row_size_out_bytes": 6.0
                                    },
                                    "columns": {
                                      "active": [
                                        "badges.userid",
                                        "badges.class"
                                      ]
                                    },
                                    "details": {
                                      "scan": {
                                        "table": "badges",
                                        "columns": [
                                          "userid",
                                          "class"
                                        ],
                                        "pushdown_predicates": [
                                          "optional: class=1 OR class=2"
                                        ],
                                        "delim_index": null,
                                        "fixed_widths": [
                                          4,
                                          2
                                        ],
                                        "varwidth": [
                                          false,
                                          false
                                        ]
                                      }
                                    }
                                  }
                                ],
                                "metrics": {
                                  "elapsed_ms": 6.260314999999995,
                                  "rows_in": 1273148,
                                  "rows_out": 384794,
                                  "row_size_in_bytes": 6.0,
                                  "row_size_out_bytes": 6.0
                                },
                                "columns": {
                                  "active": [
                                    "badges.class"
                                  ]
                                },
                                "details": {
                                  "filter": {
                                    "predicates": [
                                      "((class = 1) OR (class = 2))"
                                    ]
                                  }
                                }
                              }
                            ],
                            "metrics": {
                              "elapsed_ms": 32.417368000000025,
                              "rows_in": 1645504,
                              "rows_out": 384794,
                              "rows_in_left": 1260710,
                              "rows_in_right": 384794,
                              "row_size_in_left_bytes": 8.0,
                              "row_size_in_right_bytes": 4.0,
                              "row_size_out_bytes": 12.0
                            },
                            "columns": {
                              "active": [
                                "badges.userid"
                              ]
                            },
                            "details": {
                              "join": {
                                "join_type": "INNER",
                                "condition": "id = userid",
                                "left_keys": [],
                                "right_keys": [],
                                "delim_index": null
                              }
                            }
                          }
                        ],
                        "metrics": {
                          "elapsed_ms": 27.81954000000004,
                          "rows_in": 1645504,
                          "rows_out": 1260710,
                          "rows_in_left": 1260710,
                          "rows_in_right": 384794,
                          "row_size_in_left_bytes": 0.0,
                          "row_size_in_right_bytes": 8.0,
                          "row_size_out_bytes": 8.0
                        },
                        "columns": {
                          "active": []
                        },
                        "details": {
                          "join": {
                            "join_type": "MARK",
                            "condition": "id IS NOT DISTINCT FROM id",
                            "left_keys": [],
                            "right_keys": [],
                            "delim_index": null
                          }
                        }
                      }
                    ],
                    "metrics": {
                      "elapsed_ms": 107.20250099999998,
                      "rows_in": 2521420,
                      "rows_out": 0,
                      "rows_in_left": 1260710,
                      "rows_in_right": 1260710,
                      "row_size_in_left_bytes": 98.89313640726257,
                      "row_size_in_right_bytes": 8.0,
                      "row_size_out_bytes": 106.89313640726257
                    },
                    "columns": {
                      "active": [
                        "users.id"
                      ]
                    },
                    "details": {
                      "join": {
                        "join_type": "MARK",
                        "condition": "id IS NOT DISTINCT FROM id",
                        "left_keys": [],
                        "right_keys": [],
                        "delim_index": "1",
                        "algorithm": "delim"
                      }
                    },
                    "_deps": [
                      {
                        "id": 35,
                        "op": "Aggregate",
                        "name": "HASH_GROUP_BY",
                        "children": [],
                        "metrics": {
                          "elapsed_ms": 39.86079100000003,
                          "rows_in": null,
                          "rows_out": 1260710
                        },
                        "columns": {
                          "active": []
                        },
                        "details": {
                          "aggregate": {
                            "group_keys": [
                              "#3"
                            ],
                            "aggregates": [],
                            "algorithm": null
                          }
                        },
                        "_slot_lineage": [
                          []
                        ]
                      }
                    ]
                  }
                ],
                "metrics": {
                  "elapsed_ms": 11.075908999999996,
                  "rows_in": null,
                  "rows_out": 76721,
                  "row_size_in_bytes": 106.89313640726257,
                  "row_size_out_bytes": 106.89313640726257
                },
                "columns": {
                  "active": [
                    "users.reputation"
                  ]
                },
                "details": {
                  "filter": {
                    "predicates": [
                      "(SUBQUERY OR (reputation > 1000))"
                    ]
                  }
                }
              },
              {
                "id": 37,
                "op": "Scan",
                "name": "READ_PARQUET",
                "children": [],
                "metrics": {
                  "elapsed_ms": 44.814991000000006,
                  "rows_in": null,
                  "rows_out": 12744093,
                  "row_size_in_bytes": 0.0,
                  "row_size_out_bytes": 8.25
                },
                "columns": {
                  "active": [
                    "votes.userid",
                    "votes.bountyamount"
                  ]
                },
                "details": {
                  "scan": {
                    "table": "votes",
                    "columns": [
                      "userid",
                      "bountyamount"
                    ],
                    "pushdown_predicates": [],
                    "delim_index": null,
                    "fixed_widths": [
                      4,
                      4
                    ],
                    "varwidth": [
                      false,
                      false
                    ]
                  }
                }
              }
            ],
            "metrics": {
              "elapsed_ms": 42.483643999999884,
              "rows_in": 12820814,
              "rows_out": 100856,
              "rows_in_left": 76721,
              "rows_in_right": 12744093,
              "row_size_in_left_bytes": 107.01813640726257,
              "row_size_in_right_bytes": 8.25,
              "row_size_out_bytes": 115.26813640726257
            },
            "columns": {
              "active": [
                "posthistory.userid",
                "votes.userid"
              ]
            },
            "details": {
              "join": {
                "join_type": "LEFT",
                "condition": "UserId = userid",
                "left_keys": [],
                "right_keys": [],
                "delim_index": null
              }
            }
          }
        ],
        "metrics": {
          "elapsed_ms": 22.647053000000014,
          "rows_in": 100856,
          "rows_out": 76721,
          "row_size_in_bytes": 118.89313640726257,
          "row_size_out_bytes": 46.893136407262574
        },
        "columns": {
          "active": [
            "posthistory.userid",
            "votes.userid",
            "users.displayname",
            "users.reputation"
          ]
        },
        "details": {
          "aggregate": {
            "group_keys": [
              "#0",
              "#1",
              "#2",
              "#3",
              "#4",
              "#5",
              "#6",
              "#7",
              "#8",
              "#9",
              "#10",
              "#11"
            ],
            "aggregates": [
              "sum(#12)"
            ],
            "algorithm": null
          }
        }
      }
    ],
    "metrics": {
      "elapsed_ms": 7.784312,
      "rows_in": 76721,
      "rows_out": 76721,
      "row_size_in_bytes": 110.89313640726257,
      "row_size_out_bytes": 110.89313640726257
    },
    "columns": {
      "active": [
        "users.reputation"
      ]
    },
    "details": {
      "sort": {
        "keys": [
          {
            "expr": "uf.TotalPosts DESC",
            "asc": false,
            "nulls_first": false
          },
          {
            "expr": "reputation DESC",
            "asc": false,
            "nulls_first": false
          }
        ]
      }
    }
  },
  "_delim_registry": {
    "1": {
      "rows": 1260710,
      "key_lineage": [
        []
      ]
    }
  }
}